LICENSE
README.md
setup.cfg
setup.py
kompas3d/ConvertLibInterfaces.py
kompas3d/IFCConverter.py
kompas3d/KGAX.py
kompas3d/KompasLibrary.py
kompas3d/LDefin2D.py
kompas3d/LDefin3D.py
kompas3d/MiscellaneousHelpers.py
kompas3d/Pdf2d.py
kompas3d/kAPI2D5COM.py
kompas3d/kAPI3D5COM.py
kompas3d/kAPI5.py
kompas3d/kAPI7.py
kompas3d/ksConstants.py
kompas3d/ksConstants3D.py
kompas3d.egg-info/PKG-INFO
kompas3d.egg-info/SOURCES.txt
kompas3d.egg-info/dependency_links.txt
kompas3d.egg-info/not-zip-safe
kompas3d.egg-info/top_level.txt