Metadata-Version: 2.1
Name: kompas3d
Version: 0.20.1
Summary: Kompas 3D packages
Home-page: https://www.ascon.net/
Author: Asem Nurzhanova
Author-email: asem.nurzhanova@outlook.com
License: UNKNOWN
Platform: UNKNOWN
Classifier: Programming Language :: Python :: 3.8
Classifier: License :: OSI Approved :: MIT License
Classifier: Operating System :: OS Independent
Requires-Python: >=3.8
License-File: LICENSE
